odoo/addons/ssi_equipment_request/README.rst
odoo/addons/ssi_equipment_request/__init__.py
odoo/addons/ssi_equipment_request/__manifest__.py
odoo/addons/ssi_equipment_request/menu.xml
odoo/addons/ssi_equipment_request/data/approval_template_data.xml
odoo/addons/ssi_equipment_request/data/base_automation_data.xml
odoo/addons/ssi_equipment_request/data/equipment_request_operation_data.xml
odoo/addons/ssi_equipment_request/data/equipment_request_policy_data.xml
odoo/addons/ssi_equipment_request/data/equipment_request_policy_field_data.xml
odoo/addons/ssi_equipment_request/data/ir_actions_server_data.xml
odoo/addons/ssi_equipment_request/data/ir_sequence_data.xml
odoo/addons/ssi_equipment_request/data/policy_template_data.xml
odoo/addons/ssi_equipment_request/data/sequence_template_data.xml
odoo/addons/ssi_equipment_request/i18n/ssi_equipment_request.pot
odoo/addons/ssi_equipment_request/models/__init__.py
odoo/addons/ssi_equipment_request/models/employee_equipment_request_route.py
odoo/addons/ssi_equipment_request/models/equipment_request.py
odoo/addons/ssi_equipment_request/models/equipment_request_line.py
odoo/addons/ssi_equipment_request/models/equipment_request_operation.py
odoo/addons/ssi_equipment_request/models/equipment_request_policy.py
odoo/addons/ssi_equipment_request/models/equipment_request_policy_field.py
odoo/addons/ssi_equipment_request/models/equipment_request_policy_rule.py
odoo/addons/ssi_equipment_request/models/equipment_request_type.py
odoo/addons/ssi_equipment_request/models/hr_employee.py
odoo/addons/ssi_equipment_request/models/stock_move.py
odoo/addons/ssi_equipment_request/models/stock_rule.py
odoo/addons/ssi_equipment_request/models/stock_warehouse.py
odoo/addons/ssi_equipment_request/security/ir.model.access.csv
odoo/addons/ssi_equipment_request/security/ir_module_category_data.xml
odoo/addons/ssi_equipment_request/security/ir_rule_data.xml
odoo/addons/ssi_equipment_request/security/res_group_data.xml
odoo14_addon_ssi_equipment_request-14.0.4.2.0.dist-info/METADATA
odoo14_addon_ssi_equipment_request-14.0.4.2.0.dist-info/WHEEL
odoo14_addon_ssi_equipment_request-14.0.4.2.0.dist-info/top_level.txt
odoo14_addon_ssi_equipment_request-14.0.4.2.0.dist-info/RECORD
